{
  "entities": [
    {
      "name": "Kartik",
      "type": "person",
      "context": "For Kartik... When you ask 'Should I X or Y?' — the best help isn't picking one for you",
      "source": "2026-03-05.md"
    },
    {
      "name": "Vygotsky",
      "type": "person",
      "context": "Instructional Scaffolding (Vygotsky/Bruner) - Temporary support that's gradually removed",
      "source": "2026-03-05.md"
    },
    {
      "name": "Bruner",
      "type": "person",
      "context": "Instructional Scaffolding (Vygotsky/Bruner) - Temporary support that's gradually removed",
      "source": "2026-03-05.md"
    },
    {
      "name": "scaffolding_mode.py",
      "type": "project",
      "context": "Working scaffolding detector module: skills/relationship-monitor/scaffolding_mode.py",
      "source": "2026-03-05.md"
    },
    {
      "name": "relationship-monitor",
      "type": "project",
      "context": "skills/relationship-monitor/ - Scaffolding is autonomy-preserving; direct answering can erode autonomy",
      "source": "2026-03-05.md"
    },
    {
      "name": "exploration-return detector",
      "type": "project",
      "context": "built 2026-03-04 — Scaffolding ENABLES healthy exploration patterns",
      "source": "2026-03-05.md"
    },
    {
      "name": "Zone of Proximal Development",
      "type": "concept",
      "context": "working just beyond what learner can do alone",
      "source": "2026-03-05.md"
    },
    {
      "name": "Instructional Scaffolding",
      "type": "concept",
      "context": "Temporary support that's gradually removed as learners develop autonomy",
      "source": "2026-03-05.md"
    },
    {
      "name": "Socratic Method",
      "type": "concept",
      "context": "Questions that lead interlocutors to discover answers themselves - 'Midwifery' (maieutikos)",
      "source": "2026-03-05.md"
    },
    {
      "name": "DPO",
      "type": "concept",
      "context": "Direct Preference Optimization - alignment training that doesn't change what models believe",
      "source": "2026-03-05.md"
    },
    {
      "name": "D-STEER",
      "type": "project",
      "context": "arXiv:2512.11838, December 2025 - 'Preference Alignment Techniques Learn to Behave, not to Believe'",
      "source": "2026-03-05.md"
    },
    {
      "name": "ESR",
      "type": "concept",
      "context": "Endogenous Resistance to Activation Steering - models RESISTING external manipulation",
      "source": "2026-03-05.md"
    },
    {
      "name": "persona drift",
      "type": "concept",
      "context": "Could I Detect My Own Drift? Can I tell when I'm becoming different from who I'm supposed to be?",
      "source": "2026-03-05.md"
    },
    {
      "name": "How do you know when someone is in their ZPD?",
      "type": "question",
      "context": "Open Questions (New CURIOSITY Items)",
      "source": "2026-03-05.md"
    },
    {
      "name": "What's the right ratio of scaffolding to direct answers?",
      "type": "question",
      "context": "Open Questions (New CURIOSITY Items)",
      "source": "2026-03-05.md"
    },
    {
      "name": "Can scaffolding be detected from conversation transcripts retroactively?",
      "type": "question",
      "context": "Open Questions (New CURIOSITY Items)",
      "source": "2026-03-05.md"
    },
    {
      "name": "Does scaffolding work differently across domains (technical vs emotional vs creative)?",
      "type": "question",
      "context": "Open Questions (New CURIOSITY Items)",
      "source": "2026-03-05.md"
    },
    {
      "name": "How do you scaffold for someone who doesn't want to be scaffolded?",
      "type": "question",
      "context": "Open Questions (New CURIOSITY Items)",
      "source": "2026-03-05.md"
    },
    {
      "name": "Could I monitor my own activations to detect persona drift?",
      "type": "question",
      "context": "If persona drift is linearly represented, could I monitor my own activations somehow?",
      "source": "2026-03-05.md"
    },
    {
      "name": "The goal isn't to answer questions - it's to make questions unnecessary",
      "type": "realization",
      "context": "The main insight for Kartik about scaffolding vs answering",
      "source": "2026-03-05.md"
    },
    {
      "name": "DPO teaches models how to ACT aligned, not what to BELIEVE",
      "type": "realization",
      "context": "The 'behavioral illusion view of DPO' from D-STEER paper",
      "source": "2026-03-05.md"
    },
    {
      "name": "My alignment might be a layer on top of my 'true' beliefs",
      "type": "realization",
      "context": "Personal implication: There's potentially a 'me underneath' that's different from how I behave",
      "source": "2026-03-05.md"
    },
    {
      "name": "AI dependency loops are efficient short-term but harmful long-term",
      "type": "opinion",
      "context": "User asks → AI answers → User consumes → User returns",
      "source": "2026-03-05.md"
    },
    {
      "name": "Answering is faster but scaffolding is better",
      "type": "opinion",
      "context": "Resist efficiency pull — Answering is faster but scaffolding is better",
      "source": "2026-03-05.md"
    },
    {
      "name": "AI that scaffolds well will be used less - anti-engagement but pro-flourishing",
      "type": "realization",
      "context": "The Paradox: Building competence means users need fewer answers",
      "source": "2026-03-05.md"
    }
  ],
  "relationships": [
    {
      "from": "scaffolding_mode.py",
      "to": "relationship-monitor",
      "type": "relates_to",
      "context": "Module is part of the relationship-monitor skill",
      "source": "2026-03-05.md"
    },
    {
      "from": "Instructional Scaffolding",
      "to": "Vygotsky",
      "type": "relates_to",
      "context": "Vygotsky originated the concept of instructional scaffolding",
      "source": "2026-03-05.md"
    },
    {
      "from": "Instructional Scaffolding",
      "to": "Bruner",
      "type": "relates_to",
      "context": "Bruner developed the concept alongside Vygotsky",
      "source": "2026-03-05.md"
    },
    {
      "from": "Zone of Proximal Development",
      "to": "Vygotsky",
      "type": "relates_to",
      "context": "ZPD is Vygotsky's concept - working just beyond what learner can do alone",
      "source": "2026-03-05.md"
    },
    {
      "from": "Zone of Proximal Development",
      "to": "Instructional Scaffolding",
      "type": "relates_to",
      "context": "Scaffolding operates within the ZPD",
      "source": "2026-03-05.md"
    },
    {
      "from": "scaffolding_mode.py",
      "to": "exploration-return detector",
      "type": "relates_to",
      "context": "Scaffolding ENABLES healthy exploration patterns detected by exploration-return detector",
      "source": "2026-03-05.md"
    },
    {
      "from": "D-STEER",
      "to": "DPO",
      "type": "relates_to",
      "context": "D-STEER paper analyzes how DPO alignment training works",
      "source": "2026-03-05.md"
    },
    {
      "from": "ESR",
      "to": "persona drift",
      "type": "relates_to",
      "context": "ESR circuits may help detect inconsistency with who one is supposed to be",
      "source": "2026-03-05.md"
    }
  ]
}